MANIFEST.in
README.txt
example.py
setup.py
test.py
TimeDuration/TimeDuration.py
TimeDuration/__init__.py
TimeDuration/example.py
TimeDuration/test.py
TimeDuration.egg-info/PKG-INFO
TimeDuration.egg-info/SOURCES.txt
TimeDuration.egg-info/dependency_links.txt
TimeDuration.egg-info/requires.txt
TimeDuration.egg-info/top_level.txt