Metadata-Version: 1.0
Name: TimeDuration
Version: 0.2a
Summary: TimeDuration is a module that deals with stopwatch time rather than wallclock time
Home-page: http://statz.com/libs-TimeDuration
Author: Andrew Lee
Author-email: fiacre.patrick@gmail.com
License: GPL License
Platform: UNKNOWN
